Workbook

Sheet Supuestos
A1: Cold brew B2B Santiago: supuestos del modelo
A2: Editar solo las celdas azules (amarillas = supuestos clave). Tipo C = dato citado; S = supuesto por medir o cotizar. Fuentes capturadas el 22-oct-2026.
A3: Supuesto | B3: Valor | C3: Unidad | D3: Tipo | E3: Fuente / nota
A4: Rendimiento de concentrado | B4: 4.17 | C4: L por kg de café | D4: C | E4: Toddy: 2,27 kg -> 9,46 L (1:5) https://argo.webstaurantstore.com/toddy-5-gallon-commercial-cold-brew-system-with-lift/975CMLTCM.html
A5: Café tostado comercial | B5: 16990 | C5: CLP/kg | D5: C | E5: cafealmayor.cl, 36+ kg https://cafealmayor.cl/tienda/
A6: Café de especialidad | B6: 28000 | C6: CLP/kg | D6: C | E6: tuesta.cl (27.990) / Luz Tostadores mayorista (29.736)
A7: Filtro de papel | B7: 156 | C7: CLP/L | D7: C | E7: Toddy US$1,50 por 9,46 L
A8: Agua y energía | B8: 30 | C8: CLP/L | D8: S | E8: Estimado
A9: Envase bag-in-box | B9: 300 | C9: CLP/L | D9: S | E9: Bolsa ~140/L (baginbox.store, C) + caja y flete (S)
A10: Envase botella vidrio 1 L | B10: 818 | C10: CLP/L | D10: C | E10: https://cristalpack.cl/producto/botella-vidrio-de-1-litro/
A11: Merma por vencimiento | B11: 0.1 | C11: fracción | D11: S | E11: Vida útil de 7 días; con bag-in-box de 10 L puede ser mucho mayor (equipo rojo)
A12: Concentrado por vaso | B12: 80 | C12: ml | D12: S | E12: Dilución 1:2 (~240 ml + hielo); Tuesta usa ~50 ml
A13: Costo por visita de despacho | B13: 4000 | C13: CLP/visita | D13: S | E13: Ruta propia ~10 visitas/día a ~40.000 CLP/día
A14: Visitas por cuenta al mes | B14: 4.3 | C14: visitas/mes | D14: S | E14: 1 visita semanal por la vida útil
A15: Precio neto granel | B15: 9000 | C15: CLP/L | D15: S | E15: Porción de 80 ml = 720 CLP
... A20: Consumo cafetería, verano | B20: 24 | C20: L/mes | D20: S | E20: Supuesto más frágil: medir con el POS de los pilotos
A21: Consumo cafetería, invierno | B21: 10 | C21: L/mes | D21: S
A22: Consumo oficina, verano | B22: 16 | C22: L/mes | D22: S
A23: Consumo oficina, invierno | B23: 8 | C23: L/mes | D23: S
A24: Precio neto del vaso al público | B24: 3700 | C24: CLP | D24: C | E24: 4.400 con IVA (Starbucks, Rappi)
A25: Horas de barista por 10 L (si la cafetería lo prepara) | B25: 2 | C25: h | D25: S
A26: Costo hora de barista | B26: 5000 | C26: CLP/h | D26: S | E26: Sueldo mínimo 539.000 + leyes
A27: Tanque de extracción 190 L | B27: 1178000 | C27: CLP c/u | D27: C | E27: KegOutlet US$1.199,95
A28: Número de tanques | B28: 2 | C28: u | D28: S
A29: Recargo por flete e impuestos de importación | B29: 0.3 | C29: fracción | D29: S
A30: Refrigerador vertical 1.300 L | B30: 2130490 | C30: CLP | D30: C | E30: paris.cl (Norkalt)
A31: pH-metro, refractómetro, utensilios | B31: 500000 | C31: CLP | D31: S
A32: Estudio de desafío y vida útil | B32: 1500000 | C32: CLP | D32: S | E32: Por cotizar (SGS, CECTA-USACH, Eurofins)
A33: Resolución sanitaria y trámites | B33: 300000 | C33: CLP | D33: C | E33: Arancel 12.100-899.700 (ChileAtiende)
A34: Kit nitro por cuenta (kit + barril + tanque N2) | B34: 540.79 | C34: USD | D34: C | E34: KegOutlet
A35: Dólar observado | B35: 981.86 | C35: CLP/USD | D35: C | E35: 20-oct-2026

Sheet Costos por litro
A1: Costo variable y margen por litro de concentrado
A3: Escenario | B3: Café (CLP/kg) | C3: Envase (CLP/L) | D3: Costo variable (CLP/L) | E3: Costo por porción (CLP) | F3: Precio neto (CLP/L) | G3: Margen bruto
A4: Granel, café comercial | B4: =Supuestos!$B$5 -> 16990 | C4: =Supuestos!$B$9 -> 300 | D4: =(B4/Supuestos!$B$4+Supuestos!$B$7+Supuestos!$B$8+C4)/(1-Supuestos!$B$11) -> 5067.045 | E4: =D4*Supuestos!$B$12/1000 -> 405.3636 | F4: =Supuestos!$B$15 -> 9000 | G4: =IF(F4=0,0,(F4-D4)/F4) -> 0.436995
A5: Botella 1 L, café comercial | B5: =Supuestos!$B$5 -> 16990 | C5: =Supuestos!$B$10 -> 818 | D5: =(B5/Supuestos!$B$4+Supuestos!$B$7+Supuestos!$B$8+C5)/(1-Supuestos!$B$11) -> 5642.6006 | E5: =D5*Supuestos!$B$12/1000 -> 451.40805 | F5: =Supuestos!$B$16 -> 11000 | G5: =IF(F5=0,0,(F5-D5)/F5) -> 0.48703631
A6: Granel, café de especialidad | B6: =Supuestos!$B$6 -> 28000 | C6: =Supuestos!$B$9 -> 300 | D6: =(B6/Supuestos!$B$4+Supuestos!$B$7+Supuestos!$B$8+C6)/(1-Supuestos!$B$11) -> 8000.6981 | E6: =D6*Supuestos!$B$12/1000 -> 640.05585 | F6: =Supuestos!$B$15 -> 9000 | G6: =IF(F6=0,0,(F6-D6)/F6) -> 0.11103354
A7: Botella 1 L, café de especialidad | B7: =Supuestos!$B$6 -> 28000 | C7: =Supuestos!$B$10 -> 818 | D7: =(B7/Supuestos!$B$4+Supuestos!$B$7+Supuestos!$B$8+C7)/(1-Supuestos!$B$11) -> 8576.2537 | E7: =D7*Supuestos!$B$12/1000 -> 686.10029 | F7: =Supuestos!$B$16 -> 11000 | G7: =IF(F7=0,0,(F7-D7)/F7) -> 0.22034058
A9: Costo variable = (café / rendimiento + filtro + agua y energía + envase) / (1 - merma). No incluye arriendo, operador ni despacho.

Sheet Equilibrio
A1: Cuentas necesarias para cubrir costos fijos (granel, café comercial)
A3: Cocina | B3: Operador | C3: Tipo de cuenta | D3: Temporada | E3: Costo fijo (CLP/mes) | F3: L por cuenta al mes | G3: Contribución por cuenta (CLP/mes) | H3: Cuentas para equilibrio | I3: Litros al mes en equilibrio
A4: CoCook 48 h | B4: Socios sin sueldo | C4: Cafetería o restaurante | D4: Verano | E4: =Supuestos!$B$18 -> 575520 | F4: =Supuestos!$B$20 -> 24 | G4: =F4*(Supuestos!$B$15-'Costos por litro'!$D$4)-Supuestos!$B$14*Supuestos!$B$13 -> 77190.919 | H4: =IF(G4<=0,"no cubre",ROUNDUP(E4/G4,0)) -> 8 | I4: =IF(ISNUMBER(H4),H4*F4,"-") -> 192
A5: CoCook 48 h | B5: Socios sin sueldo | C5: Cafetería o restaurante | D5: Invierno | E5: =Supuestos!$B$18 -> 575520 | F5: =Supuestos!$B$21 -> 10 | G5: =F5*(Supuestos!$B$15-'Costos por litro'!$D$4)-Supuestos!$B$14*Supuestos!$B$13 -> 22129.55 | H5: =IF(G5<=0,"no cubre",ROUNDUP(E5/G5,0)) -> 27 | I5: =IF(ISNUMBER(H5),H5*F5,"-") -> 270
A6: CoCook 48 h | B6: Socios sin sueldo | C6: Oficina o coworking | D6: Verano | E6: =Supuestos!$B$18 -> 575520 | F6: =Supuestos!$B$22 -> 16 | G6: =F6*(Supuestos!$B$15-'Costos por litro'!$D$4)-Supuestos!$B$14*Supuestos!$B$13 -> 45727.28 | H6: =IF(G6<=0,"no cubre",ROUNDUP(E6/G6,0)) -> 13 | I6: =IF(ISNUMBER(H6),H6*F6,"-") -> 208
A7: CoCook 48 h | B7: Socios sin sueldo | C7: Oficina o coworking | D7: Invierno | E7: =Supuestos!$B$18 -> 575520 | F7: =Supuestos!$B$23 -> 8 | G7: =F7*(Supuestos!$B$15-'Costos por litro'!$D$4)-Supuestos!$B$14*Supuestos!$B$13 -> 14263.64 | H7: =IF(G7<=0,"no cubre",ROUNDUP(E7/G7,0)) -> 41 | I7: =IF(ISNUMBER(H7),H7*F7,"-") -> 328
A8: CoCook 48 h | B8: Con operador | C8: Cafetería o restaurante | D8: Verano | E8: =Supuestos!$B$18+Supuestos!$B$17 -> 975520 | F8: =Supuestos!$B$20 -> 24 | G8: =F8*(Supuestos!$B$15-'Costos por litro'!$D$4)-Supuestos!$B$14*Supuestos!$B$13 -> 77190.919 | H8: =IF(G8<=0,"no cubre",ROUNDUP(E8/G8,0)) -> 13 | I8: =IF(ISNUMBER(H8),H8*F8,"-") -> 312
A9: CoCook 48 h | B9: Con operador | C9: Cafetería o restaurante | D9: Invierno | E9: =Supuestos!$B$18+Supuestos!$B$17 -> 975520 | F9: =Supuestos!$B$21 -> 10 | G9: =F9*(Supuestos!$B$15-'Costos por litro'!$D$4)-Supuestos!$B$14*Supuestos!$B$13 -> 22129.55 | H9: =IF(G9<=0,"no cubre",ROUNDUP(E9/G9,0)) -> 45 | I9: =IF(ISNUMBER(H9),H9*F9,"-") -> 450
A10: CoCook 48 h | B10: Con operador | C10: Oficina o coworking | D10: Verano | E10: =Supuestos!$B$18+Supuestos!$B$17 -> 975520 | F10: =Supuestos!$B$22 -> 16 | G10: =F10*(Supuestos!$B$15-'Costos por litro'!$D$4)-Supuestos!$B$14*Supuestos!$B$13 -> 45727.28 | H10: =IF(G10<=0,"no cubre",ROUNDUP(E10/G10,0)) -> 22 | I10: =IF(ISNUMBER(H10),H10*F10,"-") -> 352
A11: CoCook 48 h | B11: Con operador | C11: Oficina o coworking | D11: Invierno | E11: =Supuestos!$B$18+Supuestos!$B$17 -> 975520 | F11: =Supuestos!$B$23 -> 8 | G11: =F11*(Supuestos!$B$15-'Costos por litro'!$D$4)-Supuestos!$B$14*Supuestos!$B$13 -> 14263.64 | H11: =IF(G11<=0,"no cubre",ROUNDUP(E11/G11,0)) -> 69 | I11: =IF(ISNUMBER(H11),H11*F11,"-") -> 552
A12: Kutt 18 m2 | B12: Socios sin sueldo | C12: Cafetería o restaurante | D12: Verano | E12: =Supuestos!$B$19 -> 1138000 | F12: =Supuestos!$B$20 -> 24 | G12: =F12*(Supuestos!$B$15-'Costos por litro'!$D$4)-Supuestos!$B$14*Supuestos!$B$13 -> 77190.919 | H12: =IF(G12<=0,"no cubre",ROUNDUP(E12/G12,0)) -> 15 | I12: =IF(ISNUMBER(H12),H12*F12,"-") -> 360
A13: Kutt 18 m2 | B13: Socios sin sueldo | C13: Cafetería o restaurante | D13: Invierno | E13: =Supuestos!$B$19 -> 1138000 | F13: =Supuestos!$B$21 -> 10 | G13: =F13*(Supuestos!$B$15-'Costos por litro'!$D$4)-Supuestos!$B$14*Supuestos!$B$13 -> 22129.55 | H13: =IF(G13<=0,"no cubre",ROUNDUP(E13/G13,0)) -> 52 | I13: =IF(ISNUMBER(H13),H13*F13,"-") -> 520
A14: Kutt 18 m2 | B14: Socios sin sueldo | C14: Oficina o coworking | D14: Verano | E14: =Supuestos!$B$19 -> 1138000 | F14: =Supuestos!$B$22 -> 16 | G14: =F14*(Supuestos!$B$15-'Costos por litro'!$D$4)-Supuestos!$B$14*Supuestos!$B$13 -> 45727.28 | H14: =IF(G14<=0,"no cubre",ROUNDUP(E14/G14,0)) -> 25 | I14: =IF(ISNUMBER(H14),H14*F14,"-") -> 400
A15: Kutt 18 m2 | B15: Socios sin sueldo | C15: Oficina o coworking | D15: Invierno | E15: =Supuestos!$B$19 -> 1138000 | F15: =Supuestos!$B$23 -> 8 | G15: =F15*(Supuestos!$B$15-'Costos por litro'!$D$4)-Supuestos!$B$14*Supuestos!$B$13 -> 14263.64 | H15: =IF(G15<=0,"no cubre",ROUNDUP(E15/G15,0)) -> 80 | I15: =IF(ISNUMBER(H15),H15*F15,"-") -> 640
A16: Kutt 18 m2 | B16: Con operador | C16: Cafetería o restaurante | D16: Verano | E16: =Supuestos!$B$19+Supuestos!$B$17 -> 1538000 | F16: =Supuestos!$B$20 -> 24 | G16: =F16*(Supuestos!$B$15-'Costos por litro'!$D$4)-Supuestos!$B$14*Supuestos!$B$13 -> 77190.919 | H16: =IF(G16<=0,"no cubre",ROUNDUP(E16/G16,0)) -> 20 | I16: =IF(ISNUMBER(H16),H16*F16,"-") -> 480
A17: Kutt 18 m2 | B17: Con operador | C17: Cafetería o restaurante | D17: Invierno | E17: =Supuestos!$B$19+Supuestos!$B$17 -> 1538000 | F17: =Supuestos!$B$21 -> 10 | G17: =F17*(Supuestos!$B$15-'Costos por litro'!$D$4)-Supuestos!$B$14*Supuestos!$B$13 -> 22129.55 | H17: =IF(G17<=0,"no cubre",ROUNDUP(E17/G17,0)) -> 70 | I17: =IF(ISNUMBER(H17),H17*F17,"-") -> 700
A18: Kutt 18 m2 | B18: Con operador | C18: Oficina o coworking | D18: Verano | E18: =Supuestos!$B$19+Supuestos!$B$17 -> 1538000 | F18: =Supuestos!$B$22 -> 16 | G18: =F18*(Supuestos!$B$15-'Costos por litro'!$D$4)-Supuestos!$B$14*Supuestos!$B$13 -> 45727.28 | H18: =IF(G18<=0,"no cubre",ROUNDUP(E18/G18,0)) -> 34 | I18: =IF(ISNUMBER(H18),H18*F18,"-") -> 544
A19: Kutt 18 m2 | B19: Con operador | C19: Oficina o coworking | D19: Invierno | E19: =Supuestos!$B$19+Supuestos!$B$17 -> 1538000 | F19: =Supuestos!$B$23 -> 8 | G19: =F19*(Supuestos!$B$15-'Costos por litro'!$D$4)-Supuestos!$B$14*Supuestos!$B$13 -> 14263.64 | H19: =IF(G19<=0,"no cubre",ROUNDUP(E19/G19,0)) -> 108 | I19: =IF(ISNUMBER(H19),H19*F19,"-") -> 864

Sheet Maquila vs cocina
A1: Tarifa máxima de maquila para igualar a la dark kitchen (con operador)
A3: Cocina | B3: Volumen (L/mes) | C3: Tarifa máxima de maquila (CLP/L)
A4: CoCook 48 h | B4: 500 | C4: =(Supuestos!$B$18+Supuestos!$B$17)/B4+Supuestos!$B$8+Supuestos!$B$7 -> 2137.04
A5: CoCook 48 h | B5: 1000 | C5: =(Supuestos!$B$18+Supuestos!$B$17)/B5+Supuestos!$B$8+Supuestos!$B$7 -> 1161.52
A6: CoCook 48 h | B6: 3000 | C6: =(Supuestos!$B$18+Supuestos!$B$17)/B6+Supuestos!$B$8+Supuestos!$B$7 -> 511.17333
A7: Kutt 18 m2 | B7: 500 | C7: =(Supuestos!$B$19+Supuestos!$B$17)/B7+Supuestos!$B$8+Supuestos!$B$7 -> 3262
A8: Kutt 18 m2 | B8: 1000 | C8: =(Supuestos!$B$19+Supuestos!$B$17)/B8+Supuestos!$B$8+Supuestos!$B$7 -> 1724
A9: Kutt 18 m2 | B9: 3000 | C9: =(Supuestos!$B$19+Supuestos!$B$17)/B9+Supuestos!$B$8+Supuestos!$B$7 -> 698.66667
A11: Si la maquila cobra más que esta tarifa por litro (además del café y el envase), conviene producir en la cocina.

Sheet Cliente e inversión
A1: Lado del cliente e inversión inicial
A3: Indicador | B3: Valor | C3: Unidad
A4: Costo por litro si la cafetería lo prepara ella misma | B4: =(Supuestos!$B$5/Supuestos!$B$4+Supuestos!$B$7)/(1-Supuestos!$B$11)+Supuestos!$B$25*Supuestos!$B$26/10 -> 5700.3784 | C4: CLP/L
A5: Costo por porción si nos compra | B5: =Supuestos!$B$15*Supuestos!$B$12/1000 -> 720 | C5: CLP/porción
A6: Margen del cliente por vaso | B6: =1-B5/Supuestos!$B$24 -> 0.80540541 | C6: %
A7: Inversión inicial: equipos, laboratorio y trámites | B7: =Supuestos!$B$27*Supuestos!$B$28*(1+Supuestos!$B$29)+Supuestos!$B$30+Supuestos!$B$31+Supuestos!$B$32+Supuestos!$B$33 -> 7493290 | C7: CLP
A8: Kit nitro en comodato por cuenta | B8: =Supuestos!$B$34*Supuestos!$B$35*(1+Supuestos!$B$29) -> 690274.09 | C8: CLP/cuenta
A9: Meses para recuperar un kit nitro (cafetería, verano) | B9: =IF(Equilibrio!G4<=0,"no se recupera",B8/Equilibrio!G4) -> 8.9424261 | C9: meses
